pygate_grpc/client.py
pygate_grpc/config.py
pygate_grpc/data.py
pygate_grpc/deals.py
pygate_grpc/decorators.py
pygate_grpc/errors.py
pygate_grpc/exceptions.py
pygate_grpc/storage_info.py
pygate_grpc/storage_jobs.py
pygate_grpc/types.py
pygate_grpc/wallet.py
pygate_grpc/admin/__init__.py
pygate_grpc/admin/storage_jobs.py
pygate_grpc/admin/users.py
pygate_grpc/admin/wallet.py
pygate_grpc-2.0.0.dist-info/LICENSE
pygate_grpc-2.0.0.dist-info/METADATA
pygate_grpc-2.0.0.dist-info/WHEEL
pygate_grpc-2.0.0.dist-info/top_level.txt
pygate_grpc-2.0.0.dist-info/RECORD
