Metadata-Version: 2.1
Name: pygate-grpc
Version: 2.0.0
Summary: A Python interface to Textile's Powergate Filecoin API
Home-page: https://github.com/pygate/pygate-gRPC
Author: Pygate Team
Author-email: info@pygate.com
License: MIT
Platform: UNKNOWN
Classifier: Development Status :: 3 - Alpha
Classifier: Intended Audience :: Developers
Classifier: Intended Audience :: Information Technology
Classifier: Topic :: Software Development :: Build Tools
Classifier: License :: OSI Approved :: MIT License
Classifier: Programming Language :: Python :: 3
Classifier: Programming Language :: Python :: 3.4
Classifier: Programming Language :: Python :: 3.5
Classifier: Programming Language :: Python :: 3.6
Requires-Dist: deprecated (==1.2.11)
Requires-Dist: grpc-powergate-client (==2.1.0)
Requires-Dist: grpcio (==1.35.0)
Requires-Dist: mypy-extensions (==0.4.3)
Requires-Dist: protobuf (==3.15.1)
Requires-Dist: six (==1.15.0)
Requires-Dist: wrapt (==1.12.1)
